metametrics/__init__.py
metametrics/metametrics.py
metametrics/version.py
metametrics-0.0.1.dist-info/LICENSE
metametrics-0.0.1.dist-info/METADATA
metametrics-0.0.1.dist-info/WHEEL
metametrics-0.0.1.dist-info/top_level.txt
metametrics-0.0.1.dist-info/RECORD
